slobot/configuration.py
slobot/feetech.py
slobot/feetech_frame.py
slobot/fps_gauge.py
slobot/fps_metric.py
slobot/genesis.py
slobot/gradio_dashboard_app.py
slobot/gradio_image_app.py
slobot/gradio_qpos_app.py
slobot/gradio_video_app.py
slobot/image_streams.py
slobot/sim_client.py
slobot/simulation_frame.py
slobot/simulation_frame_paths.py
slobot/so_arm_100.py
slobot/video_streams.py
slobot/video_writer.py
slobot/config/__init__.py
slobot/config/assets/cup.stl
slobot/config/trs_so_arm100/CHANGELOG.md
slobot/config/trs_so_arm100/LICENSE
slobot/config/trs_so_arm100/README.md
slobot/config/trs_so_arm100/scene.xml
slobot/config/trs_so_arm100/so_arm100.png
slobot/config/trs_so_arm100/so_arm100.xml
slobot/config/trs_so_arm100/assets/Base.stl
slobot/config/trs_so_arm100/assets/Base_Motor.stl
slobot/config/trs_so_arm100/assets/Fixed_Jaw.stl
slobot/config/trs_so_arm100/assets/Fixed_Jaw_Collision_1.stl
slobot/config/trs_so_arm100/assets/Fixed_Jaw_Collision_2.stl
slobot/config/trs_so_arm100/assets/Fixed_Jaw_Motor.stl
slobot/config/trs_so_arm100/assets/Lower_Arm.stl
slobot/config/trs_so_arm100/assets/Lower_Arm_Motor.stl
slobot/config/trs_so_arm100/assets/Moving_Jaw.stl
slobot/config/trs_so_arm100/assets/Moving_Jaw_Collision_1.stl
slobot/config/trs_so_arm100/assets/Moving_Jaw_Collision_2.stl
slobot/config/trs_so_arm100/assets/Moving_Jaw_Collision_3.stl
slobot/config/trs_so_arm100/assets/Rotation_Pitch.stl
slobot/config/trs_so_arm100/assets/Rotation_Pitch_Motor.stl
slobot/config/trs_so_arm100/assets/Upper_Arm.stl
slobot/config/trs_so_arm100/assets/Upper_Arm_Motor.stl
slobot/config/trs_so_arm100/assets/Wrist_Pitch_Roll.stl
slobot/config/trs_so_arm100/assets/Wrist_Pitch_Roll_Motor.stl
slobot/lerobot/episode_loader.py
slobot/lerobot/episode_replayer.py
slobot/lerobot/frame_delay_detector.py
slobot/lerobot/hold_state_detector.py
slobot/lerobot/policy_evaluator.py
slobot/lerobot/pytorch_optimizer.py
slobot/lerobot/sim_dataset_generator.py
slobot/metrics/rerun_metrics.py
slobot-0.1.18.dist-info/licenses/LICENSE
slobot-0.1.18.dist-info/METADATA
slobot-0.1.18.dist-info/WHEEL
slobot-0.1.18.dist-info/top_level.txt
slobot-0.1.18.dist-info/RECORD
