Metadata-Version: 2.4
Name: slobot
Version: 0.1.18
License-File: LICENSE
Requires-Dist: torch
Requires-Dist: feetech-servo-sdk
Requires-Dist: datafusion
Requires-Dist: gradio
Requires-Dist: ipykernel
Requires-Dist: modal
Requires-Dist: pyscipopt
Dynamic: license-file
